cloud_init_gen/__init__.py
cloud_init_gen/cloud_init_doc.py
cloud_init_gen/exceptions.py
cloud_init_gen/part.py
cloud_init_gen/part_type.py
cloud_init_gen/py.typed
cloud_init_gen/renderable.py
cloud_init_gen/simple.py
cloud_init_gen/typehints.py
cloud_init_gen/version.py
cloud_init_gen-1.2.0.dist-info/entry_points.txt
cloud_init_gen-1.2.0.dist-info/LICENSE
cloud_init_gen-1.2.0.dist-info/WHEEL
cloud_init_gen-1.2.0.dist-info/METADATA
cloud_init_gen-1.2.0.dist-info/RECORD
