Metadata-Version: 2.1
Name: cloud-init-gen
Version: 1.2.0
Summary: Simplified generation of cloud-init user-data content
Home-page: https://github.com/sammck/cloud-init-gen
License: MIT
Keywords: cloud-init,user-data,userdata,ec2,boto3,aws,pulumi
Author: Sam McKelvie
Author-email: dev@mckelvie.org
Requires-Python: >=3.8,<4.0
Classifier: License :: OSI Approved :: MIT License
Classifier: Programming Language :: Python :: 3
Classifier: Programming Language :: Python :: 3.10
Classifier: Programming Language :: Python :: 3.8
Classifier: Programming Language :: Python :: 3.9
Requires-Dist: PyYAML (>=6.0,<7.0)
Project-URL: Repository, https://github.com/sammck/cloud-init-gen.git
